README.md
setup.py
lightwave2/__init__.py
lightwave2/lightwave2.py
lightwave2.egg-info/PKG-INFO
lightwave2.egg-info/SOURCES.txt
lightwave2.egg-info/dependency_links.txt
lightwave2.egg-info/requires.txt
lightwave2.egg-info/top_level.txt