Metadata-Version: 2.1
Name: lightwave2
Version: 0.8.16
Summary: Controls for Lightwave RF second generation devices
Home-page: https://github.com/bigbadblunt/lightwave2
Author: Bryan Blunt
Author-email: bryan@blunt.me.uk
License: UNKNOWN
Platform: UNKNOWN
Classifier: Programming Language :: Python :: 3
Classifier: License :: OSI Approved :: MIT License
Classifier: Operating System :: OS Independent
